AUTHORS
CHANGES
DESCRIPTION
LICENCE
MANIFEST.in
README
setup.cfg
setup.py
django_kibrit/__init__.py
django_kibrit/base.py
django_kibrit/constants.py
django_kibrit/context_processors.py
django_kibrit.egg-info/PKG-INFO
django_kibrit.egg-info/SOURCES.txt
django_kibrit.egg-info/dependency_links.txt
django_kibrit.egg-info/not-zip-safe
django_kibrit.egg-info/top_level.txt