Metadata-Version: 1.1
Name: django-kibrit
Version: 0.1.3
Summary: Kibrit -- an open source git version parser for Django
